README.md
setup.py
bin/kachery-token
bin/mt-cat
bin/mt-download
bin/mt-find
bin/mt-ls
bin/mt-resolve-key-path
bin/mt-snapshot
mlprocessors/__init__.py
mlprocessors/consolecapture.py
mlprocessors/core.py
mlprocessors/createjobs.py
mlprocessors/defaultjobhandler.py
mlprocessors/execute.py
mlprocessors/jobhandler.py
mlprocessors/jobqueue.py
mlprocessors/mountainjob.py
mlprocessors/mountainjobresult.py
mlprocessors/paralleljobhandler.py
mlprocessors/registry.py
mlprocessors/shellscript.py
mlprocessors/slurmjobhandler.py
mlprocessors/temporarydirectory.py
mlprocessors/validators.py
mountainclient/__init__.py
mountainclient/aux.py
mountainclient/filelock.py
mountainclient/kachery_tokens.py
mountainclient/mountainclient.py
mountainclient/mountainclientlocal.py
mountainclient/mountainremoteclient.py
mountainclient/mttyping.py
mountainclient/sha1cache.py
mountainclient/steady_download_and_compute_sha1.py
mountaintools/__init__.py
mountaintools.egg-info/PKG-INFO
mountaintools.egg-info/SOURCES.txt
mountaintools.egg-info/dependency_links.txt
mountaintools.egg-info/requires.txt
mountaintools.egg-info/top_level.txt
mtlogging/__init__.py
mtlogging/mtlogging.py
vdomr/__init__.py
vdomr/component.py
vdomr/helpers.py
vdomr/vdom.py
vdomr/vdomr.py
vdomr/vdomrserver.py
vdomr/components/__init__.py
vdomr/components/components.py
vdomr/devel/__init__.py
vdomr/devel/devel.py