Metadata-Version: 1.1
Name: mountaintools
Version: 0.7.0
Summary: Tools for reproducible scientific research
Home-page: UNKNOWN
Author: Jeremy Magland
Author-email: jmagland@flatironinstitute.org
License: UNKNOWN
Platform: UNKNOWN
Classifier: Programming Language :: Python :: 3
Classifier: License :: OSI Approved :: Apache Software License
Classifier: Operating System :: OS Independent
